sentry_dramatiq/__init__.py
sentry_dramatiq-0.3.3.dist-info/LICENSE
sentry_dramatiq-0.3.3.dist-info/METADATA
sentry_dramatiq-0.3.3.dist-info/WHEEL
sentry_dramatiq-0.3.3.dist-info/top_level.txt
sentry_dramatiq-0.3.3.dist-info/RECORD
