Metadata-Version: 2.1
Name: sentry-dramatiq
Version: 0.3.3
Summary: Dramatiq task processor integration for the Sentry SDK
Home-page: https://github.com/jmagnusson/sentry-dramatiq
Author: Jacob Magnusson
Author-email: m@jacobian.se
License: BSD
Platform: any
Classifier: Development Status :: 3 - Alpha
Classifier: Intended Audience :: Developers
Classifier: License :: OSI Approved :: MIT License
Classifier: Operating System :: OS Independent
Classifier: Programming Language :: Python
Classifier: Programming Language :: Python :: 3.5
Classifier: Programming Language :: Python :: 3.6
Classifier: Programming Language :: Python :: 3.7
Classifier: Programming Language :: Python :: 3.8
License-File: LICENSE
Requires-Dist: dramatiq (>=1.9)
Requires-Dist: sentry-sdk
Provides-Extra: test
Requires-Dist: flake8 ; extra == 'test'
Requires-Dist: isort ; extra == 'test'
Requires-Dist: black ; extra == 'test'
Requires-Dist: pytest ; extra == 'test'
Requires-Dist: coverage ; extra == 'test'
